odoo/addons/shopfloor_base_multicompany/README.rst
odoo/addons/shopfloor_base_multicompany/__init__.py
odoo/addons/shopfloor_base_multicompany/__manifest__.py
odoo/addons/shopfloor_base_multicompany/i18n/it.po
odoo/addons/shopfloor_base_multicompany/i18n/shopfloor_base_multicompany.pot
odoo/addons/shopfloor_base_multicompany/models/__init__.py
odoo/addons/shopfloor_base_multicompany/models/shopfloor_app.py
odoo/addons/shopfloor_base_multicompany/readme/CONTRIBUTORS.rst
odoo/addons/shopfloor_base_multicompany/readme/DESCRIPTION.rst
odoo/addons/shopfloor_base_multicompany/services/__init__.py
odoo/addons/shopfloor_base_multicompany/services/service.py
odoo/addons/shopfloor_base_multicompany/static/description/icon.png
odoo/addons/shopfloor_base_multicompany/static/description/index.html
odoo/addons/shopfloor_base_multicompany/tests/__init__.py
odoo/addons/shopfloor_base_multicompany/tests/test_company_validation.py
odoo/addons/shopfloor_base_multicompany/views/shopfloor_app.xml
odoo14_addon_shopfloor_base_multicompany-14.0.1.0.1.dev8.dist-info/METADATA
odoo14_addon_shopfloor_base_multicompany-14.0.1.0.1.dev8.dist-info/WHEEL
odoo14_addon_shopfloor_base_multicompany-14.0.1.0.1.dev8.dist-info/top_level.txt
odoo14_addon_shopfloor_base_multicompany-14.0.1.0.1.dev8.dist-info/RECORD
